kotonohagetter.py
kotonohagetter-0.0.2.dist-info/LICENSE
kotonohagetter-0.0.2.dist-info/METADATA
kotonohagetter-0.0.2.dist-info/WHEEL
kotonohagetter-0.0.2.dist-info/entry_points.txt
kotonohagetter-0.0.2.dist-info/top_level.txt
kotonohagetter-0.0.2.dist-info/RECORD
