Metadata-Version: 2.1
Name: kotonohagetter
Version: 0.0.2
Summary: A package for visualization of aggregate data of players in "Kotoha Tango"
Home-page: https://github.com/plumchloride/kotonohatango-getter
Author: rikito ohnishi
Author-email: ohnishi.rikito@gmail.com
License: UNKNOWN
Project-URL: Bug Tracker, https://github.com/plumchloride/kotonohatango-getter
Platform: UNKNOWN
Classifier: Programming Language :: Python :: 3
Classifier: License :: OSI Approved :: MIT License
Classifier: Operating System :: OS Independent
Requires-Python: >=3.7
License-File: LICENSE
